fa_scrapper/__init__.py
fa_scrapper-0.4.0.dist-info/METADATA
fa_scrapper-0.4.0.dist-info/WHEEL
fa_scrapper-0.4.0.dist-info/RECORD
